[
  { "name": "Ares", "division": "Division 1", "logo": "ares.png" },
  { "name": "Boreal", "division": "Division 1", "logo": "boreal.png" },
  { "name": "Cyclone", "division": "Division 1", "logo": "cyclone.png" },
  { "name": "Ink Souls Perla", "division": "Division 1", "logo": "ink_souls_perla.png" },
  { "name": "E", "division": "Division 1", "logo": "ares.png" },
  { "name": "F", "division": "Division 1", "logo": "boreal.png" },
  { "name": "G", "division": "Division 1", "logo": "cyclone.png" },
  { "name": "O", "division": "Division 1", "logo": "cyclone.png" },
  { "name": "H", "division": "Division 1", "logo": "ink_souls_perla.png" },
  { "name": "Draco", "division": "Division 2", "logo": "draco.png" },
  { "name": "Equinox", "division": "Division 2", "logo": "equinox.png" },
  { "name": "Falkor", "division": "Division 2", "logo": "falkor.png" },
  { "name": "Draco", "division": "Division 2", "logo": "draco.png" },
  { "name": "T", "division": "Division 2", "logo": "equinox.png" },
  { "name": "Y", "division": "Division 2", "logo": "falkor.png" },
  { "name": "L", "division": "Division 2", "logo": "equinox.png" },
  { "name": "M", "division": "Division 2", "logo": "falkor.png" },
  { "name": "Golem", "division": "Division 3", "logo": "golem.png" },
  { "name": "Helix", "division": "Division 3", "logo": "helix.png" },
  { "name": "Ion", "division": "Division 3", "logo": "ion.png" },
  { "name": "Caca", "division": "Division 3", "logo": "caca.png" },
  { "name": "B", "division": "Division 3", "logo": "golem.png" },
  { "name": "A", "division": "Division 3", "logo": "helix.png" },
  { "name": "Z", "division": "Division 3", "logo": "ion.png" },
  { "name": "U", "division": "Division 3", "logo": "caca.png" }
]
